{
    "name": "Example world",
    "width": 500,
    "height": 500,
    "playerStartX": 5,
    "playerStartY": 5,
    "defaultField": {
        "accessable": true,
        "imageName": "/images/world/accessable.png"
    },
    "items": {
        "plants": [
            {
                "x": 1,
                "y": 1,
                "plant": ":/mapdata/plants/healing-herb.json"
            },
            {
                "x": 20,
                "y": 20,
                "plant": ":/mapdata/plants/healing-herb.json"
            },
            {
                "x": 16,
                "y": 5,
                "plant": ":/mapdata/plants/healing-herb.json"
            },
            {
                "x": 18,
                "y": 6,
                "plant": ":/mapdata/plants/healing-herb.json"
            },
            {
                "x": 6,
                "y": 17,
                "plant": ":/mapdata/plants/healing-herb.json"
            },
            {
                "x": 6,
                "y": 19,
                "plant": ":/mapdata/plants/healing-herb.json"
            },
            {
                "x": 6,
                "y": 21,
                "plant": ":/mapdata/plants/healing-herb.json"
            },
            {
                "x": 8,
                "y": 21,
                "plant": ":/mapdata/plants/healing-herb.json"
            },
            {
                "x": 10,
                "y": 21,
                "plant": ":/mapdata/plants/healing-herb.json"
            }
        ],
        "trees": [
            {
                "x": 26,
                "y": 16,
                "tree": ":/mapdata/trees/tree-1.json"
            },
            {
                "x": 16,
                "y": 0,
                "tree": ":/mapdata/trees/tree-1.json"
            },
            {
                "x": 22,
                "y": 0,
                "tree": ":/mapdata/trees/tree-1.json"
            },
            {
                "x": 24,
                "y": 0,
                "tree": ":/mapdata/trees/tree-1.json"
            },
            {
                "x": 26,
                "y": 1,
                "tree": ":/mapdata/trees/tree-1.json"
            },
            {
                "x": 16,
                "y": 12,
                "tree": ":/mapdata/trees/tree-1.json"
            }
        ]
    },
    "fields": [
        {
            "x": 6,
            "y": 8,
            "accessable": false,
            "imageName": "/images/world/unaccessable.png"
        },
        {
            "x": 6,
            "y": 9,
            "accessable": false,
            "imageName": "/images/world/unaccessable.png"
        },
        {
            "x": 6,
            "y": 10,
            "accessable": false,
            "imageName": "/images/world/unaccessable.png"
        }
    ]
}
